LICENSE.txt
README.md
setup.py
rocketHiba/__init__.py
rocketHiba/rocketHiba.py
rocketHiba.egg-info/PKG-INFO
rocketHiba.egg-info/SOURCES.txt
rocketHiba.egg-info/dependency_links.txt
rocketHiba.egg-info/top_level.txt