Metadata-Version: 2.1
Name: rocketHiba
Version: 1.0.0
Summary: An awesome package that does something
Home-page: http://pypi.python.org/pypi/rocket-uploader/
Author: OUCHENE HibetElrahamne
Author-email: hibaouchene51@gmail.com
License: LICENSE.txt
License-File: LICENSE.txt
